slashml/__init__.py
slashml/model_deployment.py
slashml/speech_to_text.py
slashml/text_summarization.py
slashml/text_to_speech.py
slashml/utils.py
slashml-0.1.6.dist-info/LICENSE.txt
slashml-0.1.6.dist-info/METADATA
slashml-0.1.6.dist-info/WHEEL
slashml-0.1.6.dist-info/top_level.txt
slashml-0.1.6.dist-info/RECORD
